sayou/healthcare/health/README.md
sayou/healthcare/health/__init__.py
sayou/healthcare/health/client.py
sayou/healthcare/health/crawler.py
sayou/healthcare/health/models.py
sayou/healthcare/health/utils.py
sayou/healthcare/health/parsers/__init__.py
sayou/healthcare/health/parsers/csv_writer.py
sayou/healthcare/health/parsers/download.py
sayou/healthcare/health/parsers/medicine.py
sayou/healthcare/hira/README.md
sayou/healthcare/hira/__init__.py
sayou/healthcare/hira/client.py
sayou/healthcare/hira/crawler.py
sayou/healthcare/hira/models.py
sayou/healthcare/hira/utils.py
sayou/healthcare/hira/parsers/__init__.py
sayou/healthcare/hira/parsers/download.py
sayou/healthcare/hira/parsers/excel.py
sayou/healthcare/hira/parsers/opendata.py
sayou/healthcare/nedrug/README.md
sayou/healthcare/nedrug/__init__.py
sayou/healthcare/nedrug/client.py
sayou/healthcare/nedrug/crawler.py
sayou/healthcare/nedrug/models.py
sayou/healthcare/nedrug/utils.py
sayou/healthcare/nedrug/parsers/__init__.py
sayou/healthcare/nedrug/parsers/download.py
sayou/healthcare/nedrug/parsers/excel.py
sayou_healthcare-0.0.7.dist-info/METADATA
sayou_healthcare-0.0.7.dist-info/WHEEL
sayou_healthcare-0.0.7.dist-info/licenses/LICENSE
sayou_healthcare-0.0.7.dist-info/RECORD
