Metadata-Version: 2.4
Name: sayou-healthcare
Version: 0.0.7
Summary: Sayou Healthcare for 의약품안전나라, 건강보험심사평가원, 보건의료빅데이터개방시스템, 약학정보원
Project-URL: Homepage, https://www.sayouzone.com/
Project-URL: Repository, https://github.com/sayouzone/sayou-healthcare
Author-email: Sayouzone <support@sayouzone.com>
License:                                  Apache License
License-File: LICENSE
Classifier: License :: OSI Approved :: Apache Software License
Classifier: Operating System :: OS Independent
Classifier: Programming Language :: Python :: 3.11
Classifier: Programming Language :: Python :: 3.12
Classifier: Programming Language :: Python :: 3.13
Classifier: Topic :: Software Development :: Libraries :: Application Frameworks
Requires-Python: >=3.11
Requires-Dist: beautifulsoup4>=4.14.0
Requires-Dist: lxml>=6.0.0
Requires-Dist: openpyxl>=3.1.5
Requires-Dist: pandas>=2.3.3
